covid19_jhu_data/__init__.py
covid19_jhu_data-0.0.2.dist-info/LICENSE
covid19_jhu_data-0.0.2.dist-info/METADATA
covid19_jhu_data-0.0.2.dist-info/WHEEL
covid19_jhu_data-0.0.2.dist-info/top_level.txt
covid19_jhu_data-0.0.2.dist-info/RECORD
