Metadata-Version: 2.1
Name: covid19-jhu-data
Version: 0.0.2
Summary: We use pandas to import data from https://github.com/CSSEGISandData/COVID-19
Home-page: UNKNOWN
Author: Kuo, Yao-Jen
Author-email: yaojenkuo@datainpoint.com
License: UNKNOWN
Platform: UNKNOWN
Classifier: Programming Language :: Python :: 3
Classifier: License :: OSI Approved :: MIT License
Classifier: Operating System :: OS Independent
Requires-Python: >=3.6
Requires-Dist: requests
Requires-Dist: pandas (>=1)
